{"stats":{"minecraft:used":{"minecraft:oak_fence":6,"minecraft:stripped_acacia_wood":1,"minecraft:water_bucket":7,"minecraft:snow_block":115,"minecraft:flint_and_steel":11,"minecraft:red_sandstone_slab":49,"minecraft:redstone":14,"minecraft:oak_planks":15,"minecraft:oak_sign":4,"minecraft:chest":1,"minecraft:spruce_planks":8,"minecraft:ender_chest":2,"minecraft:stone":4,"minecraft:iron_sword":9,"minecraft:redstone_block":22,"minecraft:white_shulker_box":4,"minecraft:cauldron":1,"minecraft:cobblestone_slab":7,"minecraft:quartz_stairs":204,"minecraft:player_head":93,"minecraft:oak_leaves":51,"minecraft:white_wool":2,"minecraft:torch":7,"minecraft:dirt":19,"minecraft:rail":5,"minecraft:comparator":2,"minecraft:cobblestone_wall":1,"minecraft:crossbow":669,"minecraft:campfire":2,"minecraft:infested_stone_bricks":1,"minecraft:light_blue_stained_glass":9,"minecraft:snowball":2,"minecraft:spruce_log":10,"minecraft:oak_fence_gate":3,"minecraft:redstone_torch":11,"minecraft:oak_log":13,"minecraft:glass":2,"minecraft:dark_oak_planks":1,"minecraft:lever":3,"minecraft:packed_ice":2,"minecraft:black_wool":8,"minecraft:command_block":19,"minecraft:quartz_slab":262,"minecraft:lantern":1,"minecraft:grass_block":46,"minecraft:quartz_block":11,"minecraft:spruce_trapdoor":4,"minecraft:stone_brick_stairs":153,"minecraft:stone_bricks":5,"minecraft:bedrock":1,"minecraft:repeater":2,"minecraft:potion":1,"minecraft:wooden_sword":22,"minecraft:redstone_lamp":20,"minecraft:bow":2,"minecraft:white_banner":12,"minecraft:grindstone":2,"minecraft:ice":6,"minecraft:repeating_command_block":5,"minecraft:smooth_stone_slab":97,"minecraft:egg":586,"minecraft:stone_pressure_plate":4,"minecraft:white_concrete":14,"minecraft:splash_potion":29,"minecraft:turtle_egg":67,"minecraft:command_block_minecart":7},"minecraft:custom":{"minecraft:mob_kills":3,"minecraft:play_one_minute":402610,"minecraft:open_shulker_box":18,"minecraft:leave_game":4,"minecraft:time_since_death":10479,"minecraft:climb_one_cm":879,"minecraft:time_since_rest":10499,"minecraft:sprint_one_cm":113769,"minecraft:open_enderchest":4,"minecraft:damage_taken":3034,"minecraft:walk_one_cm":251498,"minecraft:drop":428,"minecraft:damage_dealt":1164,"minecraft:fly_one_cm":5252429,"minecraft:player_kills":1,"minecraft:crouch_one_cm":13081,"minecraft:deaths":85,"minecraft:sneak_time":7928,"minecraft:walk_under_water_one_cm":152,"minecraft:boat_one_cm":13477,"minecraft:aviate_one_cm":2899,"minecraft:jump":756,"minecraft:walk_on_water_one_cm":2085,"minecraft:fall_one_cm":2337},"minecraft:dropped":{"minecraft:iron_sword":1,"minecraft:repeating_command_block":1,"minecraft:porkchop":4,"minecraft:player_head":275,"minecraft:oak_log":1,"minecraft:infested_chiseled_stone_bricks":1,"minecraft:end_stone_brick_slab":1,"minecraft:grindstone":1,"minecraft:lantern":2,"minecraft:mossy_stone_brick_slab":1,"minecraft:infested_mossy_stone_bricks":1,"minecraft:mossy_stone_brick_stairs":1,"minecraft:cracked_stone_bricks":1,"minecraft:command_block":65,"minecraft:stripped_acacia_wood":1,"minecraft:white_shulker_box":12,"minecraft:end_stone_brick_wall":1,"minecraft:elytra":1,"minecraft:grass_block":3,"minecraft:infested_stone_bricks":1,"minecraft:chiseled_stone_bricks":1,"minecraft:cobblestone_slab":1,"minecraft:birch_fence":1,"minecraft:mossy_stone_brick_wall":1,"minecraft:packed_ice":1,"minecraft:end_stone_brick_stairs":1,"minecraft:ice":2,"minecraft:torch":1,"minecraft:wooden_axe":1,"minecraft:quartz_block":1,"minecraft:mossy_stone_bricks":1,"minecraft:stone_brick_wall":1,"minecraft:snowball":75,"minecraft:diamond_helmet":1,"minecraft:stone_bricks":1,"minecraft:stonecutter":1,"minecraft:end_stone_bricks":1,"minecraft:stone_brick_stairs":1,"minecraft:oak_leaves":1,"minecraft:quartz_slab":1,"minecraft:infested_cracked_stone_bricks":1,"minecraft:stone_brick_slab":1,"minecraft:egg":19},"minecraft:picked_up":{"minecraft:end_stone_bricks":1,"minecraft:lead":64,"minecraft:ice":1,"minecraft:turtle_egg":1,"minecraft:dirt":129,"minecraft:end_stone_brick_wall":1,"minecraft:elytra":1,"minecraft:acacia_door":30,"minecraft:wooden_sword":1,"minecraft:oak_sign":7,"minecraft:player_head":313,"minecraft:mossy_stone_brick_wall":1,"minecraft:diamond_helmet":4,"minecraft:iron_sword":2,"minecraft:egg":2,"minecraft:torch":1,"minecraft:oak_pressure_plate":1,"minecraft:porkchop":4,"minecraft:sand":981,"minecraft:mossy_stone_brick_slab":1,"minecraft:repeating_command_block":1,"minecraft:command_block":66,"minecraft:lever":1,"minecraft:white_shulker_box":19,"minecraft:snowball":54},"minecraft:killed_by":{"minecraft:player":2}},"DataVersion":1976}